bigfeta/__init__.py
bigfeta/_version.py
bigfeta/bigfeta.py
bigfeta/jsongz.py
bigfeta/schemas.py
bigfeta/utils.py
bigfeta/distributed/README.md
bigfeta/distributed/allen_example_script.pbs
bigfeta/distributed/cori_example_script.sl
bigfeta/distributed/makefile
bigfeta/distributed/bin/.gitignore
bigfeta/distributed/src/Singularity.petsc
bigfeta/distributed/src/Singularity.petsc_solver
bigfeta/distributed/src/bigfeta_dist.h
bigfeta/distributed/src/bigfeta_dist_solve.c
bigfeta/distributed/src/hw_config.h
bigfeta/qctools/CheckPointMatches.py
bigfeta/qctools/CheckResiduals.py
bigfeta/qctools/CheckTransforms.py
bigfeta/qctools/README.md
bigfeta/qctools/__init__.py
bigfeta/qctools/statistics.py
bigfeta/qctools/figures/pm_map_example.png
bigfeta/qctools/figures/residual_map_example.png
bigfeta/qctools/figures/transform_map_example.png
bigfeta/solve/__init__.py
bigfeta/solve/solve_petsc.py
bigfeta/solve/solve_scipy.py
bigfeta/solve_tools/__init__.py
bigfeta/solve_tools/regularization_sweep.py
bigfeta/transform/__init__.py
bigfeta/transform/affine_model.py
bigfeta/transform/polynomial_model.py
bigfeta/transform/rotation_model.py
bigfeta/transform/similarity_model.py
bigfeta/transform/thinplatespline_model.py
bigfeta/transform/transform.py
bigfeta/transform/translation_model.py
bigfeta/transform/utils.py
bigfeta-1.1.4.dist-info/licenses/LICENSE
bigfeta-1.1.4.dist-info/METADATA
bigfeta-1.1.4.dist-info/WHEEL
bigfeta-1.1.4.dist-info/top_level.txt
bigfeta-1.1.4.dist-info/RECORD
