Metadata-Version: 2.4
Name: bigfeta
Version: 1.1.4
Summary: global alignment of features between images
Author: Dan Kapner, Russel Torres
Maintainer: Russel Torres
License: BSD 2-Clause License
Project-URL: Repository, https://github.com/AllenInstitute/BigFeta.git
Requires-Python: <3.12,>3.8
License-File: LICENSE
Requires-Dist: render-python>=2.2.1
Requires-Dist: marshmallow<3.0
Requires-Dist: argschema<2.0
Requires-Dist: numpy
Requires-Dist: scipy
Requires-Dist: pymongo==3.11.1
Requires-Dist: h5py
Requires-Dist: matplotlib
Requires-Dist: mpl_scatter_density
Requires-Dist: descartes
Requires-Dist: shapely
Requires-Dist: pathos
Provides-Extra: test
Requires-Dist: coverage>=4.1; extra == "test"
Requires-Dist: mock>=2.0.0; extra == "test"
Requires-Dist: pep8>=1.7.0; extra == "test"
Requires-Dist: pytest; extra == "test"
Requires-Dist: pytest-cov>=2.2.1; extra == "test"
Requires-Dist: pytest-pep8>=1.0.6; extra == "test"
Requires-Dist: pytest-xdist>=1.14; extra == "test"
Requires-Dist: flake8>=3.0.4; extra == "test"
Requires-Dist: pylint>=1.5.4; extra == "test"
Requires-Dist: jinja2; extra == "test"
Provides-Extra: pypi-build
Requires-Dist: build; extra == "pypi-build"
Requires-Dist: twine; extra == "pypi-build"
Dynamic: license-file
